pymodaq_plugins_zaber/VERSION
pymodaq_plugins_zaber/__init__.py
pymodaq_plugins_zaber/daq_move_plugins/__init__.py
pymodaq_plugins_zaber/daq_move_plugins/daq_move_Zaber.py
pymodaq_plugins_zaber/daq_move_plugins/daq_move_ZaberBinary.py
pymodaq_plugins_zaber/daq_viewer_plugins/__init__.py
pymodaq_plugins_zaber/daq_viewer_plugins/plugins_0D/__init__.py
pymodaq_plugins_zaber/daq_viewer_plugins/plugins_1D/__init__.py
pymodaq_plugins_zaber/daq_viewer_plugins/plugins_2D/__init__.py
pymodaq_plugins_zaber/daq_viewer_plugins/plugins_ND/__init__.py
pymodaq_plugins_zaber-2.0.2.dist-info/LICENSE
pymodaq_plugins_zaber-2.0.2.dist-info/METADATA
pymodaq_plugins_zaber-2.0.2.dist-info/WHEEL
pymodaq_plugins_zaber-2.0.2.dist-info/entry_points.txt
pymodaq_plugins_zaber-2.0.2.dist-info/top_level.txt
pymodaq_plugins_zaber-2.0.2.dist-info/RECORD
