Metadata-Version: 2.1
Name: pymodaq_plugins_zaber
Version: 2.0.2
Summary: Plugin for Zaber actuators
Home-page: https://github.com/Attolab/pymodaq_plugins_zaber
Author: Romain Geneaux
Author-email: romain.geneaux@cea.fr
License: MIT
Classifier: Programming Language :: Python :: 3
Classifier: Development Status :: 5 - Production/Stable
Classifier: Environment :: Other Environment
Classifier: Intended Audience :: Science/Research
Classifier: Topic :: Scientific/Engineering :: Human Machine Interfaces
Classifier: Topic :: Scientific/Engineering :: Visualization
Classifier: License :: OSI Approved :: MIT License
Classifier: Operating System :: OS Independent
Classifier: Topic :: Software Development :: Libraries :: Python Modules
Classifier: Topic :: Software Development :: User Interfaces
License-File: LICENSE
Requires-Dist: toml
Requires-Dist: zaber-motion
Requires-Dist: serial
Requires-Dist: pymodaq<=4.2.5,>4.0.8
